<?xml version="1.0" encoding="ISO-8859-1"?>

<slideshow>
	<image>Gallery/1.jpg</image>
	<image>Gallery/2.jpg</image>
	<image>Gallery/3.jpg</image>
	<image>Gallery/4.jpg</image>
	<image>Gallery/5.jpg</image>
	<image>Gallery/6.jpg</image>
	<image>Gallery/7.jpg</image>
	<image>Gallery/8.jpg</image>
	<image>Gallery/9.jpg</image>
	<image>Gallery/10.jpg</image>
	<image>Gallery/11.jpg</image>
	<image>Gallery/12.jpg</image>
	<image>Gallery/13.jpg</image>
	<image>Gallery/14.jpg</image>
	<image>Gallery/15.jpg</image>
	<image>Gallery/16.jpg</image>
	<image>Gallery/17.jpg</image>
	<image>Gallery/18.jpg</image>
	<image>Gallery/19.jpg</image>
	<image>Gallery/20.jpg</image>
	<image>Gallery/21.jpg</image>
	<image>Gallery/22.jpg</image>
	<image>Gallery/23.jpg</image>
	<image>Gallery/24.jpg</image>
	<image>Gallery/25.jpg</image>
	<image>Gallery/26.jpg</image>
	<image>Gallery/27.jpg</image>
	<image>Gallery/28.jpg</image>
</slideshow>
